Fifo.v
module priority_fifo #(parameter DEPTH = 8, WIDTH = 8)(
    input clk,
    input reset,
    input write_en,
    input read_en,
    input [WIDTH-1:0] data_in,
    input priority_in, // 1 = High, 0 = Low
    output reg [WIDTH-1:0] data_out,
    output reg empty,
    output reg full
);

    reg [WIDTH-1:0] high_fifo [0:DEPTH-1];
    reg [WIDTH-1:0] low_fifo [0:DEPTH-1];
    integer high_head = 0, high_tail = 0;
    integer low_head = 0, low_tail = 0;

    wire high_empty = (high_head == high_tail);
    wire low_empty = (low_head == low_tail);
    wire high_full  = ((high_tail + 1) % DEPTH == high_head);
    wire low_full   = ((low_tail + 1) % DEPTH == low_head);

    always @(posedge clk or posedge reset) begin
        if (reset) begin
            high_head <= 0; high_tail <= 0;
            low_head <= 0; low_tail <= 0;
            data_out <= 0;
            empty <= 1;
            full <= 0;
        end else begin
            // Write operation
            if (write_en) begin
                if (priority_in && !high_full) begin
                    high_fifo[high_tail] <= data_in;
                    high_tail <= (high_tail + 1) % DEPTH;
                end else if (!priority_in && !low_full) begin
                    low_fifo[low_tail] <= data_in;
                    low_tail <= (low_tail + 1) % DEPTH;
                end
            end

            // Read operation (High-priority first)
            if (read_en) begin
                if (!high_empty) begin
                    data_out <= high_fifo[high_head];
                    high_head <= (high_head + 1) % DEPTH;
                end else if (!low_empty) begin
                    data_out <= low_fifo[low_head];
                    low_head <= (low_head + 1) % DEPTH;
                end
            end

            // Update status
            empty <= (high_empty && low_empty);
            full  <= (high_full && low_full);
        end
    end
endmodule

Fifo_TB.v
module priority_fifo_tb;
    reg clk = 0, reset;
    reg write_en, read_en;
    reg [7:0] data_in;
    reg priority_in;
    wire [7:0] data_out;
    wire empty, full;

    // Instantiate the FIFO
    priority_fifo uut (
        .clk(clk), .reset(reset),
        .write_en(write_en),
        .read_en(read_en),
        .data_in(data_in),
        .priority_in(priority_in),
        .data_out(data_out),
        .empty(empty),
        .full(full)
    );

    // Clock generator: toggles every 5 time units (10ns period)
    always #5 clk = ~clk;

    // Initial block for simulation control
    initial begin
        //  Dump signals for GTKWave
        $dumpfile("priority_fifo.vcd");       // VCD output file
        $dumpvars(0, priority_fifo_tb);       // Dump everything in this module

        //  Console output
        $display("Time\tRead\tWrite\tPriority\tDataIn\tDataOut\tEmpty\tFull");
        $monitor("%0t\t%b\t%b\t%b\t\t%h\t%h\t%b\t%b",
                 $time, read_en, write_en, priority_in, data_in, data_out, empty, full);

        //  Reset
        reset = 1; write_en = 0; read_en = 0; data_in = 8'd0; priority_in = 0;
        #10 reset = 0;

        //  Write low-priority
        write_en = 1; priority_in = 0; data_in = 8'hAA; #10;
        data_in = 8'hCC; #10;

        //  Write high-priority
        priority_in = 1; data_in = 8'hBB; #10;
        data_in = 8'hDD; #10;

        //  Stop writing
        write_en = 0; #10;

        //  Read all
        read_en = 1;
        repeat (5) #10;
        read_en = 0;

        //  End
        #20 $finish;
    end
endmodule

priority_fifo.vcd
$date
	Tue Jul 15 23:07:43 2025
$end
$version
	Icarus Verilog
$end
$timescale
	1s
$end
$scope module priority_fifo_tb $end
$var wire 1 ! full $end
$var wire 1 " empty $end
$var wire 8 # data_out [7:0] $end
$var reg 1 $ clk $end
$var reg 8 % data_in [7:0] $end
$var reg 1 & priority_in $end
$var reg 1 ' read_en $end
$var reg 1 ( reset $end
$var reg 1 ) write_en $end
$scope module uut $end
$var wire 1 $ clk $end
$var wire 8 * data_in [7:0] $end
$var wire 1 & priority_in $end
$var wire 1 ' read_en $end
$var wire 1 ( reset $end
$var wire 1 ) write_en $end
$var wire 1 + low_full $end
$var wire 1 , low_empty $end
$var wire 1 - high_full $end
$var wire 1 . high_empty $end
$var parameter 32 / DEPTH $end
$var parameter 32 0 WIDTH $end
$var reg 8 1 data_out [7:0] $end
$var reg 1 " empty $end
$var reg 1 ! full $end
$var integer 32 2 high_head [31:0] $end
$var integer 32 3 high_tail [31:0] $end
$var integer 32 4 low_head [31:0] $end
$var integer 32 5 low_tail [31:0] $end
$upscope $end
$upscope $end
$enddefinitions $end
$comment Show the parameter values. $end
$dumpall
b1000 0
b1000 /
$end
#0
$dumpvars
b0 5
b0 4
b0 3
b0 2
b0 1
1.
0-
1,
0+
b0 *
0)
1(
0'
0&
b0 %
0$
b0 #
1"
0!
$end
#5
1$
#10
0$
b10101010 %
b10101010 *
1)
0(
#15
0,
b1 5
1$
#20
0$
b11001100 %
b11001100 *
#25
0"
b10 5
1$
#30
0$
b10111011 %
b10111011 *
1&
#35
0.
b1 3
1$
#40
0$
b11011101 %
b11011101 *
#45
b10 3
1$
#50
0$
0)
#55
1$
#60
0$
1'
#65
b1 2
b10111011 #
b10111011 1
1$
#70
0$
#75
1.
b10 2
b11011101 #
b11011101 1
1$
#80
0$
#85
b1 4
b10101010 #
b10101010 1
1$
#90
0$
#95
1,
b10 4
b11001100 #
b11001100 1
1$
#100
0$
#105
1"
1$
#110
0$
0'
